task3/ram2.sv
module ram2 #(
    parameter   ADDRESS_WIDTH = 8,
                DATA_WIDTH = 8
)(
    input logic clk,
    input logic w_en,
    input logic r_en,
    input logic [ADDRESS_WIDTH-1:0] w_addr,
    input logic [ADDRESS_WIDTH-1:0] r_addr,
    input logic [DATA_WIDTH-1:0] din,
    output logic [DATA_WIDTH-1:0] dout
);

logic [DATA_WIDTH-1:0] ram_array [2**ADDRESS_WIDTH-1:0];

initial begin
    $display("Loading ram.");
    $readmemh("sineram.mem", ram_array);
end;

always_ff @(posedge clk) begin
    if (w_en == 1'b1) ram_array[w_addr] <= din;
    if (r_en == 1'b1) dout <= ram_array[r_addr];
    //output is synchronous 
end
endmodule

task3/counter.sv
module counter #(
    parameter WIDTH = 8
)(
    //interface signals
    input logic clk,
    input logic rst,
    input logic en,
    input logic [WIDTH-1:0] offset,
    output logic [WIDTH-1:0] count1,
    output logic [WIDTH-1:0] count2,
);

always_ff @ (posedge clk)
    if (rst) begin 
        count1 <= {WIDTH{1'b0}};
        count2 <= {WIDTH{1'b0}};
    end
    else if(en) begin 
        count1 <= count1 + {{WIDTH-1{1'b0}}, 1'b1};
        count2 <= count1 + offset;
    end
endmodule

task3/sigdelay.sv
module sinegen #(
    parameter A_WIDTH = 8,
    parameter D_WIDTH = 8
)(
    //interface signals
    input logic clk,                    //clock
    input logic rst,                    //rest
    input logic c_en,                   //counter enable
    input logic offset,
    input logic wr,
    input logic rd,
    input logic [D_WIDTH-1:0] mic_signal,      //input data
    output logic [D_WIDTH-1:0] delayed_signal     //output data
);

    logic [A_WIDTH-1:0] address1;        //interconnect wire1
    logic [A_WIDTH-1:0] address2;        //interconnect wire2

counter addrCounter (
    .clk (clk),
    .rst (rst),
    .en (c_en),
    .offset (offset),
    .count1 (address1),
    .count2 (address2)
);

ram2 sineRam2 (
    .clk (clk),
    .w_en (wr),
    .r_en (rd),
    .w_addr (address1),
    .r_addr (address2),
    .din (mic_signal),
    .dout (delayed_signal)
);

endmodule

task3/sigdelay.vcd
$version Generated by VerilatedVcd $end
$timescale 1ps $end

 $scope module TOP $end
  $var wire  1 % c_en $end
  $var wire  1 # clk $end
  $var wire  8 * delayed_signal [7:0] $end
  $var wire  8 ) mic_signal [7:0] $end
  $var wire  1 & offset $end
  $var wire  1 ( rd $end
  $var wire  1 $ rst $end
  $var wire  1 ' wr $end
  $scope module sinegen $end
   $var wire 32 . A_WIDTH [31:0] $end
   $var wire 32 . D_WIDTH [31:0] $end
   $var wire  8 + address1 [7:0] $end
   $var wire  8 , address2 [7:0] $end
   $var wire  1 % c_en $end
   $var wire  1 # clk $end
   $var wire  8 * delayed_signal [7:0] $end
   $var wire  8 ) mic_signal [7:0] $end
   $var wire  1 & offset $end
   $var wire  1 ( rd $end
   $var wire  1 $ rst $end
   $var wire  1 ' wr $end
   $scope module addrCounter $end
    $var wire 32 . WIDTH [31:0] $end
    $var wire  1 # clk $end
    $var wire  8 + count1 [7:0] $end
    $var wire  8 , count2 [7:0] $end
    $var wire  1 % en $end
    $var wire  8 - offset [7:0] $end
    $var wire  1 $ rst $end
   $upscope $end
   $scope module sineRam2 $end
    $var wire 32 . ADDRESS_WIDTH [31:0] $end
    $var wire 32 . DATA_WIDTH [31:0] $end
    $var wire  1 # clk $end
    $var wire  8 ) din [7:0] $end
    $var wire  8 * dout [7:0] $end
    $var wire  8 , r_addr [7:0] $end
    $var wire  1 ( r_en $end
    $var wire  8 + w_addr [7:0] $end
    $var wire  1 ' w_en $end
   $upscope $end
  $upscope $end
 $upscope $end
$enddefinitions $end


#0
1#
0$
0%
p&
1'
1(
b00000000 )
b00000000 *
b00000000 +
b00000000 ,
b01000000 -
b00000000000000000000000000001000 .
#1
0#
#2
1#
b10010110 )
#3
0#
#4
1#
b11011111 )
#5
0#
#6
1#
b10010110 *
#7
0#
#8
1#
b11011111 *
#9
0#
#10
1#
b11010011 )
#11
0#
#12
1#
b10000011 )
#13
0#
#14
1#
b00111110 )
b11010011 *
#15
0#
#16
1#
b00100001 )
b10000011 *
#17
0#
#18
1#
b00101111 )
b00111110 *
#19
0#
#20
1#
b00101010 )
b00100001 *
#21
0#
#22
1#
b01000100 )
b00101111 *
#23
0#
#24
1#
b01111100 )
b00101010 *
#25
0#
#26
1#
b10011001 )
b01000100 *
#27
0#
#28
1#
b11001100 )
b01111100 *
#29
0#
#30
1#
b11011111 )
b10011001 *
#31
0#
#32
1#
b11001100 *
#33
0#
#34
1#
b10101001 )
b11011111 *
#35
0#
#36
1#
b10001010 )
#37
0#
#38
1#
b01100110 )
b10101001 *
#39
0#
#40
1#
b01000110 )
b10001010 *
#41
0#
#42
1#
b00111110 )
b01100110 *
#43
0#
#44
1#
b01100010 )
b01000110 *
#45
0#
#46
1#
b01100100 )
b00111110 *
#47
0#
#48
1#
b01001110 )
b01100010 *
#49
0#
#50
1#
b01011101 )
b01100100 *
#51
0#
#52
1#
b01001011 )
b01001110 *
#53
0#
#54
1#
b00100111 )
b01011101 *
#55
0#
#56
1#
b00011100 )
b01001011 *
#57
0#
#58
1#
b00100111 *
#59
0#
#60
1#
b00000000 )
b00011100 *
#61
0#
#62
1#
#63
0#
#64
1#
b10010100 )
b00000000 *
#65
0#
#66
1#
b11011111 )
#67
0#
#68
1#
b10010100 *
#69
0#
#70
1#
b11011111 *
#71
0#
#72
1#
#73
0#
#74
1#
b10001010 )
#75
0#
#76
1#
b00100001 )
#77
0#
#78
1#
b00101111 )
b10001010 *
#79
0#
#80
1#
b00100001 )
b00100001 *
#81
0#
#82
1#
b00000000 )
b00101111 *
#83
0#
#84
1#
b00101101 )
b00100001 *
#85
0#
#86
1#
b00110101 )
b00000000 *
#87
0#
#88
1#
b01011101 )
b00101101 *
#89
0#
#90
1#
b10101000 )
b00110101 *
#91
0#
#92
1#
b11011111 )
b01011101 *
#93
0#
#94
1#
b10101000 *
#95
0#
#96
1#
b11011111 *
#97
0#
#98
1#
#99
0#
#100
1#
b01110010 )
#101
0#
#102
1#
b00101010 )
#103
0#
#104
1#
b00011011 )
b01110010 *
#105
0#
#106
1#
b00100001 )
b00101010 *
#107
0#
#108
1#
b00011110 )
b00011011 *
#109
0#
#110
1#
b01001101 )
b00100001 *
#111
0#
#112
1#
b10010011 )
b00011110 *
#113
0#
#114
1#
b10100010 )
b01001101 *
#115
0#
#116
1#
b11010110 )
b10010011 *
#117
0#
#118
1#
b11011111 )
b10100010 *
#119
0#
#120
1#
b11010110 *
#121
0#
#122
1#
b10101100 )
b11011111 *
#123
0#
#124
1#
b10001000 )
#125
0#
#126
1#
b01011100 )
b10101100 *
#127
0#
#128
1#
b00110101 )
b10001000 *
#129
0#
#130
1#
b00111100 )
b01011100 *
#131
0#
#132
1#
b01101000 )
b00110101 *
#133
0#
#134
1#
b01100110 )
b00111100 *
#135
0#
#136
1#
b01011001 )
b01101000 *
#137
0#
#138
1#
b01101101 )
b01100110 *
#139
0#
#140
1#
b01010010 )
b01011001 *
#141
0#
#142
1#
b00101110 )
b01101101 *
#143
0#
#144
1#
b00100010 )
b01010010 *
#145
0#
#146
1#
b00011100 )
b00101110 *
#147
0#
#148
1#
b00000000 )
b00100010 *
#149
0#
#150
1#
b00011100 *
#151
0#
#152
1#
b10000110 )
b00000000 *
#153
0#
#154
1#
b11011111 )
#155
0#
#156
1#
b10000110 *
#157
0#
#158
1#
b11011111 *
#159
0#
#160
1#
#161
0#
#162
1#
b10100011 )
#163
0#
#164
1#
b00111101 )
#165
0#
#166
1#
b00101000 )
b10100011 *
#167
0#
#168
1#
b00100001 )
b00111101 *
#169
0#
#170
1#
b00000000 )
b00101000 *
#171
0#
#172
1#
b00100101 )
b00100001 *
#173
0#
#174
1#
b00101100 )
b00000000 *
#175
0#
#176
1#
b01010001 )
b00100101 *
#177
0#
#178
1#
b10101010 )
b00101100 *
#179
0#
#180
1#
b11011111 )
b01010001 *
#181
0#
#182
1#
b10101010 *
#183
0#
#184
1#
b11011111 *
#185
0#
#186
1#
b11010110 )
#187
0#
#188
1#
b01100000 )
#189
0#
#190
1#
b01000010 )
b11010110 *
#191
0#
#192
1#
b01001011 )
b01100000 *
#193
0#
#194
1#
b01001110 )
b01000010 *
#195
0#
#196
1#
b00111101 )
b01001011 *
#197
0#
#198
1#
b01010010 )
b01001110 *
#199
0#
#200
1#
b01111100 )
b00111101 *
#201
0#
#202
1#
b01110100 )
b01010010 *
#203
0#
#204
1#
b11000100 )
b01111100 *
#205
0#
#206
1#
b11011111 )
b01110100 *
#207
0#
#208
1#
b11000100 *
#209
0#
#210
1#
b10011011 )
b11011111 *
#211
0#
#212
1#
b10011100 )
#213
0#
#214
1#
b01110010 )
b10011011 *
#215
0#
#216
1#
b01010010 )
b10011100 *
#217
0#
#218
1#
b01001111 )
b01110010 *
#219
0#
#220
1#
b01100101 )
b01010010 *
#221
0#
#222
1#
b01001011 )
b01001111 *
#223
0#
#224
1#
b00111010 )
b01100101 *
#225
0#
#226
1#
b01001100 )
b01001011 *
#227
0#
#228
1#
b00101111 )
b00111010 *
#229
0#
#230
1#
b00010110 )
b01001100 *
#231
0#
#232
1#
b00010100 )
b00101111 *
#233
0#
#234
1#
b00001100 )
b00010110 *
#235
0#
#236
1#
b00000000 )
b00010100 *
#237
0#
#238
1#
b00111001 )
b00001100 *
#239
0#
#240
1#
b11011111 )
b00000000 *
#241
0#
#242
1#
b00111001 *
#243
0#
#244
1#
b11011111 *
#245
0#
#246
1#
#247
0#
#248
1#
b10101000 )
#249
0#
#250
1#
b00110111 )
#251
0#
#252
1#
b00000000 )
b10101000 *
#253
0#
#254
1#
b00111011 )
b00110111 *
#255
0#
#256
1#
b00000000 )
b00000000 *
#257
0#
#258
1#
b00001100 )
b00111011 *
#259
0#
#260
1#
b01000011 )
b00000000 *
#261
0#
#262
1#
b01000110 )
b00001100 *
#263
0#
#264
1#
b10010011 )
b01000011 *
#265
0#
#266
1#
b11011110 )
b01000110 *
#267
0#
#268
1#
b11011111 )
b10010011 *
#269
0#
#270
1#
b11011110 *
#271
0#
#272
1#
b11011111 *
#273
0#
#274
1#
b10110001 )
#275
0#
#276
1#
b00101111 )
#277
0#
#278
1#
b00011010 )
b10110001 *
#279
0#
#280
1#
b00011101 )
b00101111 *
#281
0#
#282
1#
b00101011 )
b00011010 *
#283
0#
#284
1#
b00110001 )
b00011101 *
#285
0#
#286
1#
b10001100 )
b00101011 *
#287
0#
#288
1#
b10110011 )
b00110001 *
#289
0#
#290
1#
b11001011 )
b10001100 *
#291
0#
#292
1#
b11011111 )
b10110011 *
#293
0#
#294
1#
b11001011 *
#295
0#
#296
1#
b10110001 )
b11011111 *
#297
0#
#298
1#
b01111000 )
#299
0#
#300
1#
b01101010 )
b10110001 *
#301
0#
#302
1#
b00111100 )
b01111000 *
#303
0#
#304
1#
b00110111 )
b01101010 *
#305
0#
#306
1#
b01011001 )
b00111100 *
#307
0#
#308
1#
b01111001 )
b00110111 *
#309
0#
#310
1#
b01100101 )
b01011001 *
#311
0#
#312
1#
b01101101 )
b01111001 *
#313
0#
#314
1#
b01110001 )
b01100101 *
#315
0#
#316
1#
b01000011 )
b01101101 *
#317
0#
#318
1#
b00100110 )
b01110001 *
#319
0#
#320
1#
b00100011 )
b01000011 *
#321
0#
#322
1#
b00001100 )
b00100110 *
#323
0#
#324
1#
b00000000 )
b00100011 *
#325
0#
#326
1#
b00001100 *
#327
0#
#328
1#
b10101110 )
b00000000 *
#329
0#
#330
1#
b11011111 )
#331
0#
#332
1#
b10101110 *
#333
0#
#334
1#
b11011111 *
#335
0#
#336
1#
#337
0#
#338
1#
b10001100 )
#339
0#
#340
1#
b00101110 )
#341
0#
#342
1#
b00101101 )
b10001100 *
#343
0#
#344
1#
b00000000 )
b00101110 *
#345
0#
#346
1#
b00101101 *
#347
0#
#348
1#
b00100111 )
b00000000 *
#349
0#
#350
1#
b00101100 )
#351
0#
#352
1#
b01110100 )
b00100111 *
#353
0#
#354
1#
b11000101 )
b00101100 *
#355
0#
#356
1#
b11011111 )
b01110100 *
#357
0#
#358
1#
b11000101 *
#359
0#
#360
1#
b11011111 *
#361
0#
#362
1#
b10111101 )
#363
0#
#364
1#
b01100010 )
#365
0#
#366
1#
b00110000 )
b10111101 *
#367
0#
#368
1#
b00101110 )
b01100010 *
#369
0#
#370
1#
b00100001 )
b00110000 *
#371
0#
#372
1#
b00101001 )
b00101110 *
#373
0#
#374
1#
b01100000 )
b00100001 *
#375
0#
#376
1#
b01111101 )
b00101001 *
#377
0#
#378
1#
b10110000 )
b01100000 *
#379
0#
#380
1#
b11011111 )
b01111101 *
#381
0#
#382
1#
b10110000 *
#383
0#
#384
1#
b11001110 )
b11011111 *
#385
0#
#386
1#
b10100100 )
#387
0#
#388
1#
b10000001 )
b11001110 *
#389
0#
#390
1#
b01001000 )
b10100100 *
#391
0#
#392
1#
b00101011 )
b10000001 *
#393
0#
#394
1#
b01000011 )
b01001000 *
#395
0#
#396
1#
b01011111 )
b00101011 *
#397
0#
#398
1#
b01010011 )
b01000011 *
#399
0#
#400
1#
b01100001 )
b01011111 *
#401
0#
#402
1#
b01101000 )
b01010011 *
#403
0#
#404
1#
b00111010 )
b01100001 *
#405
0#
#406
1#
b00100010 )
b01101000 *
#407
0#
#408
1#
b00011100 )
b00111010 *
#409
0#
#410
1#
b00001100 )
b00100010 *
#411
0#
#412
1#
b00000000 )
b00011100 *
#413
0#
#414
1#
b00100101 )
b00001100 *
#415
0#
#416
1#
b11011111 )
b00000000 *
#417
0#
#418
1#
b00100101 *
#419
0#
#420
1#
b11011111 *
#421
0#
#422
1#
#423
0#
#424
1#
b10110100 )
#425
0#
#426
1#
b01001110 )
#427
0#
#428
1#
b00010110 )
b10110100 *
#429
0#
#430
1#
b00111110 )
b01001110 *
#431
0#
#432
1#
b00000000 )
b00010110 *
#433
0#
#434
1#
b00111110 *
#435
0#
#436
1#
b00101110 )
b00000000 *
#437
0#
#438
1#
b00110111 )
#439
0#
#440
1#
b10001100 )
b00101110 *
#441
0#
#442
1#
b11011101 )
b00110111 *
#443
0#
#444
1#
b11011111 )
b10001100 *
#445
0#
#446
1#
b11011101 *
#447
0#
#448
1#
b11011111 *
#449
0#
#450
1#
b10111001 )
#451
0#
#452
1#
b01011001 )
#453
0#
#454
1#
b00110111 )
b10111001 *
#455
0#
#456
1#
b00101110 )
b01011001 *
#457
0#
#458
1#
b00100010 )
b00110111 *
#459
0#
#460
1#
b00101000 )
b00101110 *
#461
0#
#462
1#
b01101100 )
b00100010 *
#463
0#
#464
1#
b10011100 )
b00101000 *
#465
0#
#466
1#
b11000011 )
b01101100 *
#467
0#
#468
1#
b11011111 )
b10011100 *
#469
0#
#470
1#
b11000011 *
#471
0#
#472
1#
b10111011 )
b11011111 *
#473
0#
#474
1#
b10010100 )
#475
0#
#476
1#
b01111000 )
b10111011 *
#477
0#
#478
1#
b01000001 )
b10010100 *
#479
0#
#480
1#
b00110010 )
b01111000 *
#481
0#
#482
1#
b01010010 )
b01000001 *
#483
0#
#484
1#
b01100001 )
b00110010 *
#485
0#
#486
1#
b01010000 )
b01010010 *
#487
0#
#488
1#
b01100110 )
b01100001 *
#489
0#
#490
1#
b01100101 )
b01010000 *
#491
0#
#492
1#
b00111000 )
b01100110 *
#493
0#
#494
1#
b00100111 )
b01100101 *
#495
0#
#496
1#
b00111000 *
#497
0#
#498
1#
b00000110 )
b00100111 *
#499
0#
#500
1#
b00000000 )
#501
0#
#502
1#
b01011111 )
b00000110 *
#503
0#
#504
1#
b11011111 )
b00000000 *
#505
0#
#506
1#
b01011111 *
#507
0#
#508
1#
b11011111 *
#509
0#
#510
1#
#511
0#
#512
1#
b10100110 )
#513
0#
#514
1#
b01010000 )
#515
0#
#516
1#
b00100011 )
b10100110 *
#517
0#
#518
1#
b00110111 )
b01010000 *
#519
0#
#520
1#
b00000000 )
b00100011 *
#521
0#
#522
1#
b00010001 )
b00110111 *
#523
0#
#524
1#
b00110001 )
b00000000 *
#525
0#
#526
1#
b01001101 )
b00010001 *
#527
0#
#528
1#
b10011001 )
b00110001 *
#529
0#
#530
1#
b11011111 )
b01001101 *
#531
0#
#532
1#
b10011001 *
#533
0#
#534
1#
b11011111 *
#535
0#
#536
1#
#537
0#
#538
1#
b10001111 )
#539
0#
#540
1#
b01000101 )
#541
0#
#542
1#
b00111010 )
b10001111 *
#543
0#
#544
1#
b00111100 )
b01000101 *
#545
0#
#546
1#
b00111010 *
#547
0#
#548
1#
b01001000 )
b00111100 *
#549
0#
#550
1#
b10000101 )
#551
0#
#552
1#
b10001111 )
b01001000 *
#553
0#
#554
1#
b10111100 )
b10000101 *
#555
0#
#556
1#
b11011100 )
b10001111 *
#557
0#
#558
1#
b11011111 )
b10111100 *
#559
0#
#560
1#
b10011110 )
b11011100 *
#561
0#
#562
1#
b10001100 )
b11011111 *
#563
0#
#564
1#
b01101000 )
b10011110 *
#565
0#
#566
1#
b01000100 )
b10001100 *
#567
0#
#568
1#
b01001000 )
b01101000 *
#569
0#
#570
1#
b01100001 )
b01000100 *
#571
0#
#572
1#
b01011111 )
b01001000 *
#573
0#
#574
1#
b01001010 )
b01100001 *
#575
0#
#576
1#
b01100101 )
b01011111 *
#577
0#
#578
1#
b01001100 )
b01001010 *
#579
0#
#580
1#
b00100011 )
b01100101 *
#581
0#
#582
1#
b00010111 )
b01001100 *
#583
0#
#584
1#
b00011011 )
b00100011 *
#585
0#
#586
1#
b00000000 )
b00010111 *
#587
0#
#588
1#
b00011011 *
#589
0#
#590
1#
b10110011 )
b00000000 *
#591
0#
#592
1#
b11011111 )
#593
0#
#594
1#
b10110011 *
#595
0#
#596
1#
b11011111 *
#597
0#
#598
1#
#599
0#
#600
1#
b01111010 )
#601
0#
#602
1#
b00010111 )
#603
0#
#604
1#
b00101010 )
b01111010 *
#605
0#
#606
1#
b00001001 )
b00010111 *
#607
0#
#608
1#
b00000000 )
b00101010 *
#609
0#
#610
1#
b00101100 )
b00001001 *
#611
0#
#612
1#
b00111010 )
b00000000 *
#613
0#
#614
1#
b01101010 )
b00101100 *
#615
0#
#616
1#
b10111001 )
b00111010 *
#617
0#
#618
1#
b11011111 )
b01101010 *
#619
0#
#620
1#
b10111001 *
#621
0#
#622
1#
b11011111 *
#623
0#
#624
1#
b10111010 )
#625
0#
#626
1#
b01011110 )
#627
0#
#628
1#
b00111111 )
b10111010 *
#629
0#
#630
1#
b00110100 )
b01011110 *
#631
0#
#632
1#
b01001000 )
b00111111 *
#633
0#
#634
1#
b01000110 )
b00110100 *
#635
0#
#636
1#
b01100001 )
b01001000 *
#637
0#
#638
1#
b10001111 )
b01000110 *
#639
0#
#640
1#
b10100101 )
b01100001 *
#641
0#
#642
1#
b11010010 )
b10001111 *
#643
0#
#644
1#
b11011110 )
b10100101 *
#645
0#
#646
1#
b11000110 )
b11010010 *
#647
0#
#648
1#
b10001010 )
b11011110 *
#649
0#
#650
1#
b01111100 )
b11000110 *
#651
0#
#652
1#
b01010100 )
b10001010 *
#653
0#
#654
1#
b01000100 )
b01111100 *
#655
0#
#656
1#
b01001110 )
b01010100 *
#657
0#
#658
1#
b01101011 )
b01000100 *
#659
0#
#660
1#
b01011001 )
b01001110 *
#661
0#
#662
1#
b01010011 )
b01101011 *
#663
0#
#664
1#
b01100000 )
b01011001 *
#665
0#
#666
1#
b00111101 )
b01010011 *
#667
0#
#668
1#
b00100010 )
b01100000 *
#669
0#
#670
1#
b00011011 )
b00111101 *
#671
0#
#672
1#
b00010001 )
b00100010 *
#673
0#
#674
1#
b00000000 )
b00011011 *
#675
0#
#676
1#
b00011000 )
b00010001 *
#677
0#
#678
1#
b11011111 )
b00000000 *
#679
0#
#680
1#
b00011000 *
#681
0#
#682
1#
b11011111 *
#683
0#
#684
1#
#685
0#
#686
1#
b11000010 )
#687
0#
#688
1#
b01011110 )
#689
0#
#690
1#
b00001000 )
b11000010 *
#691
0#
#692
1#
b00110011 )
b01011110 *
#693
0#
#694
1#
b00000100 )
b00001000 *
#695
0#
#696
1#
b00000000 )
b00110011 *
#697
0#
#698
1#
b00110011 )
b00000100 *
#699
0#
#700
1#
b00111100 )
b00000000 *
#701
0#
#702
1#
b01111110 )
b00110011 *
#703
0#
#704
1#
b11000110 )
b00111100 *
#705
0#
#706
1#
b11011111 )
b01111110 *
#707
0#
#708
1#
b11000110 *
#709
0#
#710
1#
b11011111 *
#711
0#
#712
1#
b10111111 )
#713
0#
#714
1#
b01001010 )
#715
0#
#716
1#
b01000101 )
b10111111 *
#717
0#
#718
1#
b00101001 )
b01001010 *
#719
0#
#720
1#
b00111001 )
b01000101 *
#721
0#
#722
1#
b00101100 )
b00101001 *
#723
0#
#724
1#
b01110110 )
b00111001 *
#725
0#
#726
1#
b10001010 )
b00101100 *
#727
0#
#728
1#
b10101000 )
b01110110 *
#729
0#
#730
1#
b11011110 )
b10001010 *
#731
0#
#732
1#
b11011111 )
b10101000 *
#733
0#
#734
1#
b10111010 )
b11011110 *
#735
0#
#736
1#
b10000011 )
b11011111 *
#737
0#
#738
1#
b01110101 )
b10111010 *
#739
0#
#740
1#
b01000001 )
b10000011 *
#741
0#
#742
1#
b00111110 )
b01110101 *
#743
0#
#744
1#
b01010000 )
b01000001 *
#745
0#
#746
1#
b01101100 )
b00111110 *
#747
0#
#748
1#
b01011001 )
b01010000 *
#749
0#
#750
1#
b01100001 )
b01101100 *
#751
0#
#752
1#
b01100111 )
b01011001 *
#753
0#
#754
1#
b00111110 )
b01100001 *
#755
0#
#756
1#
b00100000 )
b01100111 *
#757
0#
#758
1#
b00011101 )
b00111110 *
#759
0#
#760
1#
b00001010 )
b00100000 *
#761
0#
#762
1#
b00000000 )
b00011101 *
#763
0#
#764
1#
b00110010 )
b00001010 *
#765
0#
#766
1#
b11011111 )
b00000000 *
#767
0#
#768
1#
b00110010 *
#769
0#
#770
1#
b11011111 *
#771
0#
#772
1#
#773
0#
#774
1#
b10111001 )
#775
0#
#776
1#
b01001101 )
#777
0#
#778
1#
b00010011 )
b10111001 *
#779
0#
#780
1#
b00110010 )
b01001101 *
#781
0#
#782
1#
b00000000 )
b00010011 *
#783
0#
#784
1#
b00110010 *
#785
0#
#786
1#
b00101110 )
b00000000 *
#787
0#
#788
1#
b00111011 )
#789
0#
#790
1#
b10001011 )
b00101110 *
#791
0#
#792
1#
b11011010 )
b00111011 *
#793
0#
#794
1#
b11011111 )
b10001011 *
#795
0#
#796
1#
b11011010 *
#797
0#
#798
1#
b11011111 *
#799
0#
#800
1#
b10100111 )
#801
0#
#802
1#
b01010001 )
#803
0#
#804
1#
b00110011 )
b10100111 *
#805
0#
#806
1#
b00110110 )
b01010001 *
#807
0#
#808
1#
b00101111 )
b00110011 *
#809
0#
#810
1#
b00111001 )
b00110110 *
#811
0#
#812
1#
b01110010 )
b00101111 *
#813
0#
#814
1#
b10011011 )
b00111001 *
#815
0#
#816
1#
b10110001 )
b01110010 *
#817
0#
#818
1#
b11011111 )
b10011011 *
#819
0#
#820
1#
b10110001 *
#821
0#
#822
1#
b10110000 )
b11011111 *
#823
0#
#824
1#
b10000111 )
#825
0#
#826
1#
b01110000 )
b10110000 *
#827
0#
#828
1#
b01000101 )
b10000111 *
#829
0#
#830
1#
b00110111 )
b01110000 *
#831
0#
#832
1#
b01011000 )
b01000101 *
#833
0#
#834
1#
b01100011 )
b00110111 *
#835
0#
#836
1#
b01010001 )
b01011000 *
#837
0#
#838
1#
b01100011 )
b01100011 *
#839
0#
#840
1#
b01011011 )
b01010001 *
#841
0#
#842
1#
b00110101 )
b01100011 *
#843
0#
#844
1#
b00100110 )
b01011011 *
#845
0#
#846
1#
b00100111 )
b00110101 *
#847
0#
#848
1#
b00001011 )
b00100110 *
#849
0#
#850
1#
b00000000 )
b00100111 *
#851
0#
#852
1#
b01011001 )
b00001011 *
#853
0#
#854
1#
b11011111 )
b00000000 *
#855
0#
#856
1#
b01011001 *
#857
0#
#858
1#
b11011111 *
#859
0#
#860
1#
#861
0#
#862
1#
b10100010 )
#863
0#
#864
1#
b00101110 )
#865
0#
#866
1#
b00010110 )
b10100010 *
#867
0#
#868
1#
b00101110 )
b00101110 *
#869
0#
#870
1#
b00000000 )
b00010110 *
#871
0#
#872
1#
b00001111 )
b00101110 *
#873
0#
#874
1#
b00110100 )
b00000000 *
#875
0#
#876
1#
b01001010 )
b00001111 *
#877
0#
#878
1#
b10010111 )
b00110100 *
#879
0#
#880
1#
b11011111 )
b01001010 *
#881
0#
#882
1#
b10010111 *
#883
0#
#884
1#
b11011111 *
#885
0#
#886
1#
#887
0#
#888
1#
b10011111 )
#889
0#
#890
1#
b01000110 )
#891
0#
#892
1#
b10011111 *
#893
0#
#894
1#
b00110010 )
b01000110 *
#895
0#
#896
1#
b00110110 )
#897
0#
#898
1#
b00110010 *
#899
0#
#900
1#
b10000000 )
b00110110 *
#901
0#
#902
1#
b10001000 )
#903
0#
#904
1#
b10110101 )
b10000000 *
#905
0#
#906
1#
b11011111 )
b10001000 *
#907
0#
#908
1#
b10110101 *
#909
0#
#910
1#
b10100100 )
b11011111 *
#911
0#
#912
1#
b10000101 )
#913
0#
#914
1#
b01101011 )
b10100100 *
#915
0#
#916
1#
b01000000 )
b10000101 *
#917
0#
#918
1#
b01000010 )
b01101011 *
#919
0#
#920
1#
b01011101 )
b01000000 *
#921
0#
#922
1#
b01100011 )
b01000010 *
#923
0#
#924
1#
b01010011 )
b01011101 *
#925
0#
#926
1#
b01100110 )
b01100011 *
#927
0#
#928
1#
b01011100 )
b01010011 *
#929
0#
#930
1#
b00110001 )
b01100110 *
#931
0#
#932
1#
b00101001 )
b01011100 *
#933
0#
#934
1#
b00011111 )
b00110001 *
#935
0#
#936
1#
b00000000 )
b00101001 *
#937
0#
#938
1#
b00011111 *
#939
0#
#940
1#
b10000100 )
b00000000 *
#941
0#
#942
1#
b11011111 )
#943
0#
#944
1#
b10000100 *
#945
0#
#946
1#
b11011111 *
#947
0#
#948
1#
#949
0#
#950
1#
b10001111 )
#951
0#
#952
1#
b00100011 )
#953
0#
#954
1#
b00100100 )
b10001111 *
#955
0#
#956
1#
b00101000 )
b00100011 *
#957
0#
#958
1#
b00000000 )
b00100100 *
#959
0#
#960
1#
b00100010 )
b00101000 *
#961
0#
#962
1#
b00110110 )
b00000000 *
#963
0#
#964
1#
b01010111 )
b00100010 *
#965
0#
#966
1#
b10100111 )
b00110110 *
#967
0#
#968
1#
b11011111 )
b01010111 *
#969
0#
#970
1#
b10100111 *
#971
0#
#972
1#
b11011111 *
#973
0#
#974
1#
#975
0#
#976
1#
b01111110 )
#977
0#
#978
1#
b00111011 )
#979
0#
#980
1#
b01000000 )
b01111110 *
#981
0#
#982
1#
b00101101 )
b00111011 *
#983
0#
#984
1#
b00111110 )
b01000000 *
#985
0#
#986
1#
b01001011 )
b00101101 *
#987
0#
#988
1#
b10011001 )
b00111110 *
#989
0#
#990
1#
b10001100 )
b01001011 *
#991
0#
#992
1#
b11001101 )
b10011001 *
#993
0#
#994
1#
b11011101 )
b10001100 *
#995
0#
#996
1#
b11001101 )
b11001101 *
#997
0#
#998
1#
b10001011 )
b11011101 *
#999
0#
#1000
1#
b01111101 )
b11001101 *
#1001
0#
#1002
1#
b01100011 )
b10001011 *
#1003
0#
#1004
1#
b00111100 )
b01111101 *
#1005
0#
#1006
1#
b01010000 )
b01100011 *
#1007
0#
#1008
1#
b01101000 )
b00111100 *
#1009
0#
#1010
1#
b01100001 )
b01010000 *
#1011
0#
#1012
1#
b01010110 )
b01101000 *
#1013
0#
#1014
1#
b01101011 )
b01100001 *
#1015
0#
#1016
1#
b01001100 )
b01010110 *
#1017
0#
#1018
1#
b00101000 )
b01101011 *
#1019
0#
#1020
1#
b00100100 )
b01001100 *
#1021
0#
#1022
1#
b10110001 )
b00101000 *
#1023
0#
#1024
1#
b10101111 )
b00100100 *
#1025
0#
#1026
1#
b01000000 )
b10110001 *
#1027
0#
#1028
1#
b01001110 )
b10101111 *
#1029
0#
#1030
1#
b01010111 )
b01000000 *
#1031
0#
#1032
1#
b01100000 )
b01001110 *
#1033
0#
#1034
1#
b01101011 )
b01010111 *
#1035
0#
#1036
1#
b01111001 )
b01100000 *
#1037
0#
#1038
1#
b10000111 )
b01101011 *
#1039
0#
#1040
1#
b10010010 )
b01111001 *
#1041
0#
#1042
1#
b10010110 )
b10000111 *
#1043
0#
#1044
1#
b10011000 )
b10010010 *
#1045
0#
#1046
1#
b10011101 )
b10010110 *
#1047
0#
#1048
1#
b10011000 )
b10011000 *
#1049
0#
#1050
1#
b10010001 )
b10011101 *
#1051
0#
#1052
1#
b10000110 )
b10011000 *
#1053
0#
#1054
1#
b01111010 )
b10010001 *
#1055
0#
#1056
1#
b01110001 )
b10000110 *
#1057
0#
#1058
1#
b01100011 )
b01111010 *
#1059
0#
#1060
1#
b01011011 )
b01110001 *
#1061
0#
#1062
1#
b01010001 )
b01100011 *
#1063
0#
#1064
1#
b01001010 )
b01011011 *
#1065
0#
#1066
1#
b01000100 )
b01010001 *
#1067
0#
#1068
1#
b01000111 )
b01001010 *
#1069
0#
#1070
1#
b01001111 )
b01000100 *
#1071
0#
#1072
1#
b01010100 )
b01000111 *
#1073
0#
#1074
1#
b01011100 )
b01001111 *
#1075
0#
#1076
1#
b01100101 )
b01010100 *
#1077
0#
#1078
1#
b01110100 )
b01011100 *
#1079
0#
#1080
1#
b10000010 )
b01100101 *
#1081
0#
#1082
1#
b10000111 )
b01110100 *
#1083
0#
#1084
1#
b10001111 )
b10000010 *
#1085
0#
#1086
1#
b10011000 )
b10000111 *
#1087
0#
#1088
1#
b10011100 )
b10001111 *
#1089
0#
#1090
1#
b10011001 )
b10011000 *
#1091
0#
